odoo/addons/ssi_product_stock/README.rst
odoo/addons/ssi_product_stock/__init__.py
odoo/addons/ssi_product_stock/__manifest__.py
odoo/addons/ssi_product_stock/menu.xml
odoo/addons/ssi_product_stock/static/description/icon.png
odoo14_addon_ssi_product_stock-14.0.1.2.0.dist-info/METADATA
odoo14_addon_ssi_product_stock-14.0.1.2.0.dist-info/WHEEL
odoo14_addon_ssi_product_stock-14.0.1.2.0.dist-info/top_level.txt
odoo14_addon_ssi_product_stock-14.0.1.2.0.dist-info/RECORD
